vibe_pretty_print/__init__.py
vibe_pretty_print/ctx.py
vibe_pretty_print/infra.py
vibe_pretty_print/model.py
vibe_pretty_print/runner.py
vibe_pretty_print/usecase.py
vibe_pretty_print-0.1.3.dist-info/licenses/LICENSE
vibe_pretty_print-0.1.3.dist-info/METADATA
vibe_pretty_print-0.1.3.dist-info/WHEEL
vibe_pretty_print-0.1.3.dist-info/top_level.txt
vibe_pretty_print-0.1.3.dist-info/RECORD
