Metadata-Version: 2.4
Name: vibe-pretty-print
Version: 0.1.3
Summary: A smart formatting library for JSON, XML, YAML, and text with OpenAI integration
Author-email: Khanh Ngo <akatekhanh0212@gmail.com>
License-Expression: MIT
Project-URL: Homepage, https://github.com/akatekhanh/vibe-pretty-print
Project-URL: Repository, https://github.com/akatekhanh/vibe-pretty-print
Project-URL: Issues, https://github.com/akatekhanh/vibe-pretty-print/issues
Keywords: pretty-print,json,xml,yaml,formatting,openai
Classifier: Development Status :: 4 - Beta
Classifier: Intended Audience :: Developers
Classifier: Programming Language :: Python :: 3
Classifier: Programming Language :: Python :: 3.7
Classifier: Programming Language :: Python :: 3.8
Classifier: Programming Language :: Python :: 3.9
Classifier: Programming Language :: Python :: 3.10
Classifier: Programming Language :: Python :: 3.11
Classifier: Programming Language :: Python :: 3.12
Classifier: Topic :: Software Development :: Libraries :: Python Modules
Classifier: Topic :: Text Processing :: General
Requires-Python: >=3.7
License-File: LICENSE
Requires-Dist: requests>=2.25.0
Requires-Dist: PyYAML>=5.4.0
Requires-Dist: colorama>=0.4.4
Requires-Dist: lxml>=4.6.0
Provides-Extra: dev
Requires-Dist: pytest>=6.0; extra == "dev"
Requires-Dist: pytest-cov>=2.0; extra == "dev"
Requires-Dist: black>=21.0; extra == "dev"
Requires-Dist: flake8>=3.8; extra == "dev"
Requires-Dist: mypy>=0.812; extra == "dev"
Dynamic: license-file
